[
  {
    "resourceType": "Coverage",
    "id": "cov-5934765",
    "contained": [
      {
        "resourceType": "Organization",
        "id": "org1",
        "name": "BLUE CROSS OF WISCONSIN",
        "contact": [
          {
            "purpose": {
              "coding": [
                {
                  "system": "http://terminology.hl7.org/CodeSystem/contactentity-type",
                  "code": "BILL",
                  "display": "Billing"
                }
              ]
            },
            "address": {
              "use": "billing",
              "line": [
                "PO BOX 105187"
              ],
              "city": "ATLANTA",
              "state": "GA",
              "postalCode": "30348-5187"
            }
          }
        ]
      }
    ],
    "extension": [
      {
        "url": "http://open.epic.com/FHIR/StructureDefinition/billing-organization",
        "valueReference": {
          "reference": "#org1"
        }
      }
    ],
    "identifier": [
      {
        "system": "urn:oid:1.2.840.114350.1.13.283.2.7.2.678671",
        "value": "5934765"
      },
      {
        "type": {
          "coding": [
            {
              "system": "http://terminology.hl7.org/CodeSystem/v2-0203",
              "code": "MB",
              "display": "Member Number"
            }
          ]
        },
        "value": "MSJ60249687901"
      }
    ],
    "status": "active",
    "type": {
      "text": "Indemnity"
    },
    "subscriber": {
      "reference": "Patient/pat-Z7004242",
      "display": "Mandel, Josh C"
    },
    "subscriberId": "MSJ60249687901",
    "beneficiary": {
      "reference": "Patient/pat-Z7004242",
      "display": "Mandel, Josh C"
    },
    "relationship": {
      "coding": [
        {
          "system": "http://terminology.hl7.org/CodeSystem/subscriber-relationship",
          "code": "self",
          "display": "Self"
        }
      ],
      "text": "Self"
    },
    "period": {
      "start": "2018-08-09"
    },
    "payor": [
      {
        "reference": "Organization/org-1302",
        "identifier": {
          "use": "official",
          "system": "http://open.epic.com/FHIR/StructureDefinition/payer-id",
          "value": "1302"
        },
        "display": "BLUE CROSS OF WISCONSIN"
      }
    ],
    "class": [
      {
        "type": {
          "coding": [
            {
              "system": "http://terminology.hl7.org/CodeSystem/coverage-class",
              "code": "group",
              "display": "Group"
            }
          ]
        },
        "value": "1000010"
      },
      {
        "extension": [
          {
            "url": "http://open.epic.com/FHIR/StructureDefinition/extension/epic-id",
            "valueIdentifier": {
              "use": "secondary",
              "system": "urn:oid:1.2.840.114350.1.13.283.2.7.2.698080",
              "value": "130204"
            }
          }
        ],
        "type": {
          "coding": [
            {
              "system": "http://terminology.hl7.org/CodeSystem/coverage-class",
              "code": "plan",
              "display": "Plan"
            }
          ]
        },
        "value": "130204",
        "name": "BCBS WI PPO/FEDERAL"
      }
    ],
    "order": 1
  }
]